metaerg/__init__.py
metaerg/context.py
metaerg/installation.py
metaerg/main.py
metaerg/registry.py
metaerg/calculations/__init__.py
metaerg/calculations/cluster_database.py
metaerg/calculations/codon_usage_bias.py
metaerg/datatypes/__init__.py
metaerg/datatypes/blast.py
metaerg/datatypes/excel.py
metaerg/datatypes/fasta.py
metaerg/datatypes/functional_genes.py
metaerg/datatypes/gbk.py
metaerg/datatypes/gff.py
metaerg/datatypes/ncbi_ftp.py
metaerg/datatypes/sqlite.py
metaerg/html/__init__.py
metaerg/html/html_all_genomes.py
metaerg/html/html_feature_details.py
metaerg/html/html_feature_table.py
metaerg/html/html_genome_properties_and_subsystems.py
metaerg/run_and_read/__init__.py
metaerg/run_and_read/antismash.py
metaerg/run_and_read/aragorn.py
metaerg/run_and_read/cdd.py
metaerg/run_and_read/checkm.py
metaerg/run_and_read/cmscan.py
metaerg/run_and_read/comparative_genomics.py
metaerg/run_and_read/crispr_detect.py
metaerg/run_and_read/deepsig.py
metaerg/run_and_read/diamond_and_blastn.py
metaerg/run_and_read/functional_genes.py
metaerg/run_and_read/gene_writer.py
metaerg/run_and_read/ltr_harvest.py
metaerg/run_and_read/minced.py
metaerg/run_and_read/padloc.py
metaerg/run_and_read/prodigal.py
metaerg/run_and_read/pureseqtm.py
metaerg/run_and_read/repeat_masker.py
metaerg/run_and_read/repeater.py
metaerg/run_and_read/signalp.py
metaerg/run_and_read/tmhmm.py
metaerg/run_and_read/trf.py
metaerg/run_and_read/data/__init__.py
metaerg/run_and_read/data/functional_gene_data
metaerg-2.5.10.dist-info/METADATA
metaerg-2.5.10.dist-info/WHEEL
metaerg-2.5.10.dist-info/entry_points.txt
metaerg-2.5.10.dist-info/top_level.txt
metaerg-2.5.10.dist-info/RECORD
