Metadata-Version: 2.2
Name: metaerg
Version: 2.5.10
Summary: Annotation of genomes and contigs
Home-page: https://github.com/kinestetika/MetaErg
Author: Marc Strous
Author-email: mstrous@ucalgary.ca
License: MIT
Project-URL: Source, https://github.com/kinestetika/MetaErg
Keywords: repeat-regions genes functions taxonomy
Classifier: Development Status :: 4 - Beta
Classifier: Environment :: Console
Classifier: Natural Language :: English
Classifier: Operating System :: OS Independent
Classifier: License :: OSI Approved :: MIT License
Classifier: Programming Language :: Python :: 3.10
Classifier: Topic :: Scientific/Engineering :: Bio-Informatics
Requires-Python: >=3.10
Requires-Dist: biopython
Requires-Dist: ncbi-datasets-pylib
Requires-Dist: pandas
Requires-Dist: httpx
Requires-Dist: virtualenv
Requires-Dist: h5py
Requires-Dist: pyarrow
Requires-Dist: openpyxl
Requires-Dist: tqdm
Provides-Extra: dev
Requires-Dist: setuptools; extra == "dev"
Requires-Dist: build; extra == "dev"
Requires-Dist: twine; extra == "dev"
Provides-Extra: test
Dynamic: author
Dynamic: author-email
Dynamic: classifier
Dynamic: description
Dynamic: description-content-type
Dynamic: home-page
Dynamic: keywords
Dynamic: license
Dynamic: project-url
Dynamic: provides-extra
Dynamic: requires-dist
Dynamic: requires-python
Dynamic: summary
